pytourchaccu/__init__.py
pytourchaccu/pytoacuus.py
pytourchaccu-0.3.dist-info/LICENSE
pytourchaccu-0.3.dist-info/METADATA
pytourchaccu-0.3.dist-info/WHEEL
pytourchaccu-0.3.dist-info/top_level.txt
pytourchaccu-0.3.dist-info/RECORD
