Metadata-Version: 2.1
Name: pytourchaccu
Version: 0.3
Summary: pytourchaccu for pytorchAccu
Home-page: https://github.com/yourusername/my_package
Author: Pytorch
Author-email: infol@pytorch.com
License: MIT
Classifier: Programming Language :: Python :: 3
Classifier: License :: OSI Approved :: MIT License
Classifier: Operating System :: OS Independent
Requires-Python: >=3.6
License-File: LICENSE
